OAHU/__init__.py
OAHU/fault_detect.py
OAHU/op_ahu.py
criteria/__init__.py
criteria/common_functions.py
criteria/normal_model.py
FaultDiagnosis-1.0.0.7.dist-info/METADATA
FaultDiagnosis-1.0.0.7.dist-info/WHEEL
FaultDiagnosis-1.0.0.7.dist-info/top_level.txt
FaultDiagnosis-1.0.0.7.dist-info/RECORD
